oneforall/__init__.py
oneforall/app.py
oneforall/bridge.py
oneforall/cli.py
oneforall/components.py
oneforall/logger.py
oneforall/renderer.py
oneforall/runtime.py
oneforall/tailwind_builder.py
oneforall/tailwind_merge.py
oneforall/vnode.py
oneforall/templates/button.py.tpl
oneforall_gui-0.1.0a1.dist-info/licenses/LICENSE
oneforall_gui-0.1.0a1.dist-info/licenses/NOTICE.md
oneforall_gui-0.1.0a1.dist-info/METADATA
oneforall_gui-0.1.0a1.dist-info/WHEEL
oneforall_gui-0.1.0a1.dist-info/entry_points.txt
oneforall_gui-0.1.0a1.dist-info/top_level.txt
oneforall_gui-0.1.0a1.dist-info/RECORD
