Metadata-Version: 2.4
Name: oneforall-gui
Version: 0.1.0a1
Summary: OneForAll — lightweight Python GUI toolkit using pywebview and Python-only components.
Author-email: Rohit Ahirwal <lucifer@codewithlucifer.com>
Maintainer-email: Rohit Ahirwal <lucifer@codewithlucifer.com>
License:                                  Apache License
Project-URL: Homepage, https://github.com/Rohit-Ahirwal/oneforall
Project-URL: Documentation, https://oneforall-docs.vercel.app
Project-URL: Repository, https://github.com/Rohit-Ahirwal/oneforall
Project-URL: Bug Tracker, https://github.com/Rohit-Ahirwal/oneforall/issues
Project-URL: Changelog, https://github.com/Rohit-Ahirwal/oneforall/blob/main/CHANGELOG.md
Project-URL: Funding, https://github.com/sponsors/Rohit-Ahirwal
Keywords: python,gui,pywebview,tailwind,desktop-app,framework,components,reactive
Classifier: Development Status :: 3 - Alpha
Classifier: Intended Audience :: Developers
Classifier: Topic :: Software Development :: Libraries :: Python Modules
Classifier: Topic :: Software Development :: User Interfaces
Classifier: Topic :: Desktop Environment
Classifier: Programming Language :: Python :: 3
Classifier: Programming Language :: Python :: 3.9
Classifier: Programming Language :: Python :: 3.10
Classifier: Programming Language :: Python :: 3.11
Classifier: Programming Language :: Python :: 3.12
Classifier: License :: OSI Approved :: Apache Software License
Classifier: Operating System :: OS Independent
Classifier: Operating System :: Microsoft :: Windows
Classifier: Operating System :: POSIX :: Linux
Classifier: Operating System :: MacOS
Requires-Python: >=3.9
License-File: LICENSE
License-File: NOTICE.md
Requires-Dist: pywebview>=4.0.0
Requires-Dist: typer>=0.9.0
Requires-Dist: watchdog>=3.0.0
Requires-Dist: pyinstaller>=5.0.0
Requires-Dist: jinja2>=3.0.0
Provides-Extra: dev
Requires-Dist: black>=24.0.0; extra == "dev"
Requires-Dist: isort>=5.13.0; extra == "dev"
Requires-Dist: flake8>=7.0.0; extra == "dev"
Requires-Dist: mypy>=1.11.0; extra == "dev"
Requires-Dist: pytest>=8.0.0; extra == "dev"
Requires-Dist: pytest-cov>=5.0.0; extra == "dev"
Requires-Dist: pre-commit>=4.0.0; extra == "dev"
Requires-Dist: build>=0.10.0; extra == "dev"
Requires-Dist: twine>=4.0.0; extra == "dev"
Provides-Extra: test
Requires-Dist: pytest>=8.0.0; extra == "test"
Requires-Dist: pytest-cov>=5.0.0; extra == "test"
Requires-Dist: pytest-mock>=3.14.0; extra == "test"
Requires-Dist: pytest-asyncio>=0.24.0; extra == "test"
Dynamic: license-file
